dummy_twitter_webhook_manager/twitter_webhook_manager.py
dummy_twitter_webhook_manager-0.0.1.dist-info/LICENSE
dummy_twitter_webhook_manager-0.0.1.dist-info/METADATA
dummy_twitter_webhook_manager-0.0.1.dist-info/WHEEL
dummy_twitter_webhook_manager-0.0.1.dist-info/top_level.txt
dummy_twitter_webhook_manager-0.0.1.dist-info/RECORD
